pauto/__init__.py
pauto-2.0.0.dist-info/DESCRIPTION.rst
pauto-2.0.0.dist-info/METADATA
pauto-2.0.0.dist-info/RECORD
pauto-2.0.0.dist-info/WHEEL
pauto-2.0.0.dist-info/entry_points.txt
pauto-2.0.0.dist-info/metadata.json
pauto-2.0.0.dist-info/top_level.txt
