Metadata-Version: 2.0
Name: pauto
Version: 2.0.0
Summary: A tool for scripting software demonstrations.
Home-page: https://github.com/duckinator/pauto
Author: Ellen Marie Dash
Author-email: me@duckie.co
License: MIT
Platform: UNKNOWN
Classifier: Development Status :: 3 - Alpha
Classifier: Intended Audience :: Developers
Classifier: License :: OSI Approved :: MIT License
Classifier: Programming Language :: Python :: 3
Classifier: Programming Language :: Python :: 3.2
Classifier: Programming Language :: Python :: 3.3
Classifier: Programming Language :: Python :: 3.4
Requires-Python: >=2.7, <3.0
